setup.py
Emergic/Original (FlatFile) Emergic.py
Emergic/__init__.py
Emergic/entity.py
Emergic/link.py
Emergic/network.py
Emergic/port.py
Emergic/unit.py
Emergic/value.py
Emergic.egg-info/PKG-INFO
Emergic.egg-info/SOURCES.txt
Emergic.egg-info/dependency_links.txt
Emergic.egg-info/not-zip-safe
Emergic.egg-info/top_level.txt