Metadata-Version: 1.1
Name: Emergic
Version: 0.1
Summary: Emergic Network
Home-page: https://github.com/dpleibovitz/Emergic
Author: David Pierre Leibovitz
Author-email: dpleibovitz@ieee.org
License: GPLv3
Keywords: computational architecture cognitive neural model
Platform: UNKNOWN
Classifier: Development Status :: 3 - Alpha
Classifier: Environment :: Win32 (MS Windows)
Classifier: Framework :: IDLE
Classifier: Intended Audience :: Science/Research
Classifier: License :: OSI Approved :: GNU General Public License v3 (GPLv3)
Classifier: Natural Language :: English
Classifier: Programming Language :: Python :: 2.7
Classifier: Topic :: Scientific/Engineering :: Artificial Intelligence
